scmon/__init__.py
scmon-0.1.1.data/data/LICENSE
scmon-0.1.1.data/data/README.md
scmon-0.1.1.dist-info/METADATA
scmon-0.1.1.dist-info/RECORD
scmon-0.1.1.dist-info/WHEEL
scmon-0.1.1.dist-info/top_level.txt
