Metadata-Version: 2.1
Name: scmon
Version: 0.1.1
Summary: Dev tool for restarting apps on code change
Home-page: https://github.com/krisfris/scmon
Author: Kris
Author-email: 31852063+krisfris@users.noreply.github.com
License: MIT
Platform: UNKNOWN
